{
    "authors": [
        "Denis Diderot"
    ],
    "item_id": "2-208",
    "next": "2-1030",
    "pages": "208",
    "prev": "2-1028",
    "publish_year": "1751",
    "texthtml": "<div class=\"prp-pages-output\" lang=\"fr\">\n\n<p>* BERG-BITTENHEIM, <i>ou</i> BERGBIETEN,\npetite ville de la basse Alsace.\n \n</p>\n</div>",
    "texthtml_re": "<div class=\"prp-pages-output\" lang=\"fr\">\n\n<p>* BERG-BITTENHEIM, <i>ou</i> BERGBIETEN,\npetite ville de la basse Alsace.\n \n</p>\n</div>",
    "title": "BERG-BITTENHEIM, ou BERGBIETEN",
    "tome": "2",
    "url": "https://fr.wikisource.org/wiki/L%E2%80%99Encyclop%C3%A9die/1re_%C3%A9dition/BERG-BITTENHEIM,_ou_BERGBIETEN"
}