{
    "authors": [
        "Denis Diderot"
    ],
    "enc_link": "http://enccre.academie-sciences.fr/encyclopedie/article/v2-112-0/",
    "item_id": "2-105",
    "next": "2-106",
    "pages": "12",
    "prev": "2-104",
    "publish_year": "1751",
    "texthtml": "<div class=\"prp-pages-output\" lang=\"fr\">\n\n<p>* BAFFIN’S-BAIE, <i>ou</i> BAIE DE BAFFIN, (<i>Géog.</i>) baie dans les terres arctiques : elle s’étend depuis le <i>70 jusqu’au 80 degré de latitude. Voyez</i> <a href=\"/wiki/L%E2%80%99Encyclop%C3%A9die/1re_%C3%A9dition/BAIE\" title=\"L’Encyclopédie/1re édition/BAIE\"><span class=\"sc\">Baie</span></a>. \n \n</p>\n</div>",
    "texthtml_re": "<div class=\"prp-pages-output\" lang=\"fr\">\n\n<p>* BAFFIN’S-BAIE, <i>ou</i> BAIE DE BAFFIN, (<i>Géog.</i>) baie dans les terres arctiques : elle s’étend depuis le <i>70 jusqu’au 80 degré de latitude. <span type=\"bold\">Voyez</span></i> <a href=\"/wiki/L%E2%80%99Encyclop%C3%A9die/1re_%C3%A9dition/BAIE\" title=\"L’Encyclopédie/1re édition/BAIE\"><span class=\"sc\">Baie</span></a>. \n \n</p>\n</div>",
    "title": "BAFFIN’S-BAIE, ou BAIE DE BAFFIN",
    "tome_r": "II",
    "url": "https://fr.wikisource.org/wiki/L%E2%80%99Encyclop%C3%A9die/1re_%C3%A9dition/BAFFIN%E2%80%99S-BAIE,_ou_BAIE_DE_BAFFIN"
}