{
    "authors": [
        "Denis Diderot"
    ],
    "item_id": "2-217",
    "next": "2-1133",
    "pages": "217",
    "prev": "2-1131",
    "publish_year": "1751",
    "texthtml": "<div class=\"prp-pages-output\" lang=\"fr\">\n\n<p>* BEVERUNGEN, (<i>Géog.</i>) ville d’Allemagne\nau diocese de Paderborn, &amp; au confluent de la Beve\n&amp; du Weser. <i>Long. 27. lat. 51. 40</i>.\n \n</p>\n</div>",
    "texthtml_re": "<div class=\"prp-pages-output\" lang=\"fr\">\n\n<p>* BEVERUNGEN, (<i>Géog.</i>) ville d’Allemagne\nau diocese de Paderborn, &amp; au confluent de la Beve\n&amp; du Weser. <i>Long. 27. lat. 51. 40</i>.\n \n</p>\n</div>",
    "title": "BEVERUNGEN",
    "tome": "2",
    "url": "https://fr.wikisource.org/wiki/L%E2%80%99Encyclop%C3%A9die/1re_%C3%A9dition/BEVERUNGEN"
}