{
    "authors": [
        "Denis Diderot"
    ],
    "item_id": "2-216",
    "next": "2-1122",
    "pages": "216",
    "prev": "2-1120",
    "publish_year": "1751",
    "texthtml": "<div class=\"prp-pages-output\" lang=\"fr\">\n\n<p>* BETLIS, (<i>Géog.</i>) ville d’Asie, capitale du\nCurdistan, sur la riviere de Bendmahi. <i>Long. 60. 10. lat. 37. 20</i>.\n \n</p>\n</div>",
    "texthtml_re": "<div class=\"prp-pages-output\" lang=\"fr\">\n\n<p>* BETLIS, (<i>Géog.</i>) ville d’Asie, capitale du\nCurdistan, sur la riviere de Bendmahi. <i>Long. 60. 10. lat. 37. 20</i>.\n \n</p>\n</div>",
    "title": "BETLIS",
    "tome": "2",
    "url": "https://fr.wikisource.org/wiki/L%E2%80%99Encyclop%C3%A9die/1re_%C3%A9dition/BETLIS"
}