{
    "authors": [
        "Denis Diderot",
        "Urbain de Vandenesse"
    ],
    "item_id": "2-253",
    "next": "2-1284",
    "pages": "253",
    "prev": "2-1282",
    "publish_year": "1751",
    "texthtml": "<div class=\"prp-pages-output\" lang=\"fr\">\n\n<p>* BILIMBI, s. m. (<i>Hist. nat. bot.</i>) nom d’un petit\narbre de la hauteur de huit à dix piés, appellé par\nBontius <i>billingbing</i>, &amp; par les botanistes Européens,\n<i>malus Indica fructu pentagono</i>. Il est commun dans les\njardins du Malabar ; il porte fleur &amp; fruit toute l’année ; \nil est fecond depuis la premiere année de sa\nplantation, jusqu’à la quinzieme, &amp; par-delà.\n</p><p>Bontius dit qu’on en fait un sirop qui est bon dans\nles maladies chaudes du foie, &amp; dans l’intempérie inflammatoire \ndu sang. On l’emploie aussi dans la décoction \ndu riz non pelé, comme un remede excellent\ndans les fievres ardentes &amp; continues ; car il contribue \nbeaucoup à étancher la soif, &amp; à calmer l’effervescence \nde la <i>bile</i>. Le fruit étanche la soif, la racine\nexcite le vomissement, la décoction des feuilles excite \nla sueur &amp; fait sortir la petite vérole ; elle donne\nun bain salutaire dans les douleurs des membres.\nRay, <i>hist. plant</i>. (<i>N</i>)\n \n</p>\n</div>",
    "texthtml_re": "<div class=\"prp-pages-output\" lang=\"fr\">\n\n<p>* BILIMBI, s. m. (<i>Hist. nat. bot.</i>) nom d’un petit\narbre de la hauteur de huit à dix piés, appellé par\nBontius <i>billingbing</i>, &amp; par les botanistes Européens,\n<i>malus Indica fructu pentagono</i>. Il est commun dans les\njardins du Malabar ; il porte fleur &amp; fruit toute l’année ; \nil est fecond depuis la premiere année de sa\nplantation, jusqu’à la quinzieme, &amp; par-delà.\n</p><p>Bontius dit qu’on en fait un sirop qui est bon dans\nles maladies chaudes du foie, &amp; dans l’intempérie inflammatoire \ndu sang. On l’emploie aussi dans la décoction \ndu riz non pelé, comme un remede excellent\ndans les fievres ardentes &amp; continues ; car il contribue \nbeaucoup à étancher la soif, &amp; à calmer l’effervescence \nde la <i>bile</i>. Le fruit étanche la soif, la racine\nexcite le vomissement, la décoction des feuilles excite \nla sueur &amp; fait sortir la petite vérole ; elle donne\nun bain salutaire dans les douleurs des membres.\nRay, <i>hist. plant</i>. (<i>N</i>)\n \n</p>\n</div>",
    "title": "BILIMBI",
    "tome": "2",
    "url": "https://fr.wikisource.org/wiki/L%E2%80%99Encyclop%C3%A9die/1re_%C3%A9dition/BILIMBI"
}