{
    "authors": [
        "Denis Diderot"
    ],
    "enc_link": "http://enccre.academie-sciences.fr/encyclopedie/article/v2-1306-0/",
    "item_id": "2-1309",
    "next": "2-1310",
    "pages": "257",
    "prev": "2-1308",
    "publish_year": "1751",
    "texthtml": "<div class=\"prp-pages-output\" lang=\"fr\">\n\n<p>* <i>BIMATER</i>, (<i>Myth.</i>) épithete que l’on donnoit\nà Bacchus, &amp; par laquelle on faisoit entendre que\nJupiter l’ayant porté deux mois dans sa cuisse, lui\navoit servi de mere pendant ce tems, &amp; qu’il en\navoit eu deux.\n \n</p>\n</div>",
    "texthtml_re": "<div class=\"prp-pages-output\" lang=\"fr\">\n\n<p>* <i>BIMATER</i>, (<i>Myth.</i>) épithete que l’on donnoit\nà Bacchus, &amp; par laquelle on faisoit entendre que\nJupiter l’ayant porté deux mois dans sa cuisse, lui\navoit servi de mere pendant ce tems, &amp; qu’il en\navoit eu deux.\n \n</p>\n</div>",
    "title": "BIMATER",
    "tome_r": "II",
    "url": "https://fr.wikisource.org/wiki/L%E2%80%99Encyclop%C3%A9die/1re_%C3%A9dition/BIMATER"
}