{
    "authors": [],
    "item_id": "2-321",
    "next": "2-1676",
    "pages": "321",
    "prev": "2-1674",
    "publish_year": "1751",
    "texthtml": "<div class=\"prp-pages-output\" lang=\"fr\">\n\n<p>BONDON, <i>terme de Tonnelier</i>, est une cheville de \nbois grosse &amp; courte dont on bouche le trou qu’on \nlaisse au-dessus des tonneaux, pour pouvoir les remplir \n&amp; leur donner de l’air quand on le veut.\n</p><p><i>Bondon</i> se prend aussi quelquefois pour le trou \nqu’on ferme avec la cheville appellée <i>bondon</i>. \n \n</p>\n</div>",
    "texthtml_re": "<div class=\"prp-pages-output\" lang=\"fr\">\n\n<p>BONDON, <i>terme de Tonnelier</i>, est une cheville de \nbois grosse &amp; courte dont on bouche le trou qu’on \nlaisse au-dessus des tonneaux, pour pouvoir les remplir \n&amp; leur donner de l’air quand on le veut.\n</p><p><i>Bondon</i> se prend aussi quelquefois pour le trou \nqu’on ferme avec la cheville appellée <i>bondon</i>. \n \n</p>\n</div>",
    "title": "BONDON",
    "tome": "2",
    "url": "https://fr.wikisource.org/wiki/L%E2%80%99Encyclop%C3%A9die/1re_%C3%A9dition/BONDON"
}