{
    "authors": [],
    "enc_link": "http://enccre.academie-sciences.fr/encyclopedie/article/v2-1744-0/",
    "item_id": "2-1745",
    "next": "2-1746",
    "pages": "333",
    "prev": "2-1744",
    "publish_year": "1751",
    "texthtml": "<div class=\"prp-pages-output\" lang=\"fr\">\n\n<p>BORDAILLE, s. f. <i>terme de riviere</i>, se dit de la partie \nd’un bateau foncet, voisine des rebords.\n \n</p>\n</div>",
    "texthtml_re": "<div class=\"prp-pages-output\" lang=\"fr\">\n\n<p>BORDAILLE, s. f. <i>terme de riviere</i>, se dit de la<span type=\"proposed\"> partie </span>\nd’un bateau foncet, voisine des rebords.\n \n</p>\n</div>",
    "title": "BORDAILLE",
    "tome_r": "II",
    "url": "https://fr.wikisource.org/wiki/L%E2%80%99Encyclop%C3%A9die/1re_%C3%A9dition/BORDAILLE"
}