{
    "authors": [
        "Denis Diderot"
    ],
    "enc_link": "http://enccre.academie-sciences.fr/encyclopedie/article/v2-226-0/",
    "item_id": "2-219",
    "next": "2-220",
    "pages": "32",
    "prev": "2-218",
    "publish_year": "1751",
    "texthtml": "<div class=\"prp-pages-output\" lang=\"fr\">\n\n<p>* BALCH, (<i>Géog. anc. &amp; mod.</i>) ville de Perse située dans le milieu du Chorasan, sur la riviere de Dehash. Quelques Géographes la prennent pour l’ancienne Chariaspa, ou Zariaspa, ou Bactres. \n \n</p>\n</div>",
    "texthtml_re": "<div class=\"prp-pages-output\" lang=\"fr\">\n\n<p>* BALCH, (<i>Géog. anc. &amp; mod.</i>) ville de Perse située dans le milieu du Chorasan, sur la riviere de Dehash. Quelques Géographes la prennent pour l’ancienne Chariaspa, ou Zariaspa, ou Bactres. \n \n</p>\n</div>",
    "title": "BALCH",
    "tome_r": "II",
    "url": "https://fr.wikisource.org/wiki/L%E2%80%99Encyclop%C3%A9die/1re_%C3%A9dition/BALCH"
}