{
    "authors": [
        "Edme-François Mallet"
    ],
    "item_id": "2-4",
    "next": "2-23",
    "pages": "4",
    "prev": "2-21",
    "publish_year": "1751",
    "texthtml": "<div class=\"prp-pages-output\" lang=\"fr\">\n\n<p>BAANITES, s. m. pl. (<i>Hist. ecclés.</i>) hérétiques,\nsectateurs d’un certain Baanès, qui se disoit disciple\nd’Epaphrodite, &amp; semoit les erreurs des Manichéens\ndans le <span class=\"sc\">ix</span>. siecle, vers l’an 810. Pierre de Sicile,\n<i>Hist. du Manich. renaissant</i>. Baronius, <i>A. C. 810</i>. (<i>G</i>)\n \n</p>\n</div>",
    "texthtml_re": "<div class=\"prp-pages-output\" lang=\"fr\">\n\n<p>BAANITES, s. m. pl. (<i>Hist. ecclés.</i>) hérétiques,\nsectateurs d’un certain Baanès, qui se disoit disciple\nd’Epaphrodite, &amp; semoit les erreurs des Manichéens\ndans le <span class=\"sc\">ix</span>. siecle, vers l’an 810. Pierre de Sicile,\n<i>Hist. du Manich. renaissant</i>. <span type=\"auteur_p\">Baronius</span>, <i>A. C. 810</i>. (<i>G</i>)\n \n</p>\n</div>",
    "title": "BAANITES",
    "tome": "2",
    "url": "https://fr.wikisource.org/wiki/L%E2%80%99Encyclop%C3%A9die/1re_%C3%A9dition/BAANITES"
}