{
    "authors": [
        "Denis Diderot"
    ],
    "item_id": "2-458",
    "next": "2-2537",
    "pages": "458",
    "prev": "2-2535",
    "publish_year": "1751",
    "texthtml": "<div class=\"prp-pages-output\" lang=\"fr\">\n\n<p>* BUCORNE, (<i>Myth.</i>) surnom qu’on a donné à \nBacchus, que l’on représentoit quelquefois avec une \ncorne de taureau à la main, symbole ancien du vaisseau \nà boire. \n \n</p>\n</div>",
    "texthtml_re": "<div class=\"prp-pages-output\" lang=\"fr\">\n\n<p>* BUCORNE, (<i>Myth.</i>) surnom qu’on a donné à \nBacchus, que l’on représentoit quelquefois avec une \ncorne de taureau à la main, symbole ancien du vaisseau \nà boire. \n \n</p>\n</div>",
    "title": "BUCORNE",
    "tome": "2",
    "url": "https://fr.wikisource.org/wiki/L%E2%80%99Encyclop%C3%A9die/1re_%C3%A9dition/BUCORNE"
}