{
    "authors": [],
    "item_id": "2-466",
    "next": "2-2641",
    "pages": "466",
    "prev": "2-2639",
    "publish_year": "1751",
    "texthtml": "<div class=\"prp-pages-output\" lang=\"fr\">\n\n<p>BURGLANGENFELD, (<i>Géog.</i>) petite ville forte \nd’Allemagne, dans le duché de Neubourg, entre Amberg \n&amp; Ratisbonne, sur la Nabe. \n \n</p>\n</div>",
    "texthtml_re": "<div class=\"prp-pages-output\" lang=\"fr\">\n\n<p>BURGLANGENFELD, (<i>Géog.</i>) petite ville forte \nd’Allemagne, dans le duché de Neubourg, entre Amberg \n&amp; Ratisbonne, sur la Nabe. \n \n</p>\n</div>",
    "title": "BURGLANGENFELD",
    "tome": "2",
    "url": "https://fr.wikisource.org/wiki/L%E2%80%99Encyclop%C3%A9die/1re_%C3%A9dition/BURGLANGENFELD"
}