{
    "authors": [],
    "item_id": "2-561",
    "next": "2-3073",
    "pages": "561",
    "prev": "2-3071",
    "publish_year": "1751",
    "texthtml": "<div class=\"prp-pages-output\" lang=\"fr\">\n\n<p>CALLAHUYA, (<i>Géog.</i>) province de l’Amérique méridionale au Pérou, très-fertile en mines d’or. \n \n</p>\n</div>",
    "texthtml_re": "<div class=\"prp-pages-output\" lang=\"fr\">\n\n<p>CALLAHUYA, (<i>Géog.</i>) province de l’Amérique méridionale au Pérou, très-fertile en mines d’or. \n \n</p>\n</div>",
    "title": "CALLAHUYA",
    "tome": "2",
    "url": "https://fr.wikisource.org/wiki/L%E2%80%99Encyclop%C3%A9die/1re_%C3%A9dition/CALLAHUYA"
}