{
    "authors": [
        "Jacques-Nicolas Bellin"
    ],
    "enc_link": "http://enccre.academie-sciences.fr/encyclopedie/article/v2-3094-0/",
    "item_id": "2-3093",
    "next": "2-3094",
    "pages": "563",
    "prev": "2-3092",
    "publish_year": "1751",
    "texthtml": "<div class=\"prp-pages-output\" lang=\"fr\">\n\n<p>CALMER, appaiser la tempête ; <i>il commence à </i>\n<i>calmer</i> se dit à la mer, <i>calmer, devenir calme</i>, pour\nsignifier que le vent diminue.\n</p><p>Dans un combat entre deux armées navales, le\ngrand nombre de coups de canon qui se tirent, fait\npresque toûjours <i>calmer</i>. (<i>Z</i>)\n \n</p>\n</div>",
    "texthtml_re": "<div class=\"prp-pages-output\" lang=\"fr\">\n\n<p>CALMER, appaiser la tempête ; <i>il commence à </i>\n<i>calmer</i> se dit à la mer, <i>calmer, devenir calme</i>, pour\nsignifier que le vent diminue.\n</p><p>Dans un combat entre deux armées navales, le\ngrand nombre de coups de canon qui se tirent, fait\npresque toûjours <i>calmer</i>. (<i>Z</i>)\n \n</p>\n</div>",
    "title": "CALMER",
    "tome_r": "II",
    "url": "https://fr.wikisource.org/wiki/L%E2%80%99Encyclop%C3%A9die/1re_%C3%A9dition/CALMER"
}