{
    "authors": [],
    "enc_link": "http://enccre.academie-sciences.fr/encyclopedie/article/v2-3330-0/",
    "item_id": "2-3327",
    "next": "2-3328",
    "pages": "600",
    "prev": "2-3326",
    "publish_year": "1751",
    "texthtml": "<div class=\"prp-pages-output\" lang=\"fr\">\n\n<p>CANNETILLE, s. f. (<i>Boutonnier.</i>) c’est un morceau \nde fil d’or ou d’argent trait, fin, ou faux, plus\nou moins gros, qu’on a roulé sur une longue aiguille\nde fer par le moyen d’un roüet. On employe la <i>cannetille</i> dans les broderies, les crêpines, &amp; autres ouvrages \nsemblables.\n</p><p>La fabrique &amp; l’emploi de la <i>cannetille</i> forme une\nportion du métier des Passementiers-Boutonniers.\nQuand la <i>cannetille</i> est plate &amp; luisante, pour avoir\nété serrée entre deux roues d’acier, on l’appelle <i>bouillon :</i> cette marchandise entre aussi dans la composition \ndes crêpines &amp; des broderies.\n \n</p>\n</div>",
    "texthtml_re": "<div class=\"prp-pages-output\" lang=\"fr\">\n\n<p>CANNETILLE, s. f. (<i>Boutonnier.</i>) c’est un morceau \nde fil d’or ou d’argent trait, fin, ou faux, plus\nou moins gros, qu’on a roulé sur une longue aiguille\nde fer par le moyen d’un roüet. On employe la <i>cannetille</i> dans les broderies, les crêpines, &amp; autres ouvrages \nsemblables.\n</p><p>La fabrique &amp; l’emploi de la <i>cannetille</i> forme une\nportion du métier des Passementiers-Boutonniers.\nQuand la <i>cannetille</i> est plate &amp; luisante, pour avoir\nété serrée entre deux roues d’acier, on l’appelle <i>bouillon :</i> cette marchandise entre aussi dans la composition \ndes crêpines &amp; des broderies.\n \n</p>\n</div>",
    "title": "CANNETILLE",
    "tome_r": "II",
    "url": "https://fr.wikisource.org/wiki/L%E2%80%99Encyclop%C3%A9die/1re_%C3%A9dition/CANNETILLE"
}