{
    "authors": [
        "Denis Diderot"
    ],
    "enc_link": "http://enccre.academie-sciences.fr/encyclopedie/article/v2-3429-0/",
    "item_id": "2-3426",
    "next": "2-3427",
    "pages": "629",
    "prev": "2-3425",
    "publish_year": "1751",
    "texthtml": "<div class=\"prp-pages-output\" lang=\"fr\">\n\n<p>* CAPISCOL, s. m. (<i>Hist. ecclésiastique</i>) dignitaire \nde plusieurs églises, chapitres, cathédrales ou\ncollégiales, qu’on dit être le même sous un autre nom\ndans la Provence &amp; le Languedoc, où cette dignité\nest plus ordinaire, que le chantre dans les autres Provinces : si l’on s’en rapporte à l’étymologie, la <i>capiscol</i> a la prééminence au chœur ; car <i>capiscol</i> vient,\nà ce qu’on prétend, de <i><span class=\"lang-la\" lang=\"la\">caput chori</span>, le premier au chœur</i>.\n \n</p>\n</div>",
    "texthtml_re": "<div class=\"prp-pages-output\" lang=\"fr\">\n\n<p>* CAPISCOL, s. m. (<i>Hist. ecclésiastique</i>) dignitaire \nde plusieurs églises, chapitres, cathédrales ou\ncollégiales, qu’on dit être le même sous un autre nom\ndans la Provence &amp; le Languedoc, où cette dignité\nest plus ordinaire, que le chantre dans les autres Provinces : si l’on s’en rapporte à l’étymologie, la <i>capiscol</i> a la prééminence au chœur ; car <i>capiscol</i> vient,\nà ce qu’on prétend, de <i><span class=\"lang-la\" lang=\"la\">caput chori</span>, le premier au chœur</i>.\n \n</p>\n</div>",
    "title": "CAPISCOL",
    "tome_r": "II",
    "url": "https://fr.wikisource.org/wiki/L%E2%80%99Encyclop%C3%A9die/1re_%C3%A9dition/CAPISCOL"
}