{
    "authors": [],
    "item_id": "2-702",
    "next": "2-3740",
    "pages": "702",
    "prev": "2-3738",
    "publish_year": "1751",
    "texthtml": "<div class=\"prp-pages-output\" lang=\"fr\">\n\n<p>CARRELER, v. act. c’est paver une chambre, une salle, <i>&amp;c.</i> avec des carreaux. Ce travail s’exécute au mortier &amp; à la brique. On commence par répandre sur la surface à <i>carreler</i> une couche plus ou moins épaisse d’excellent mortier ; on applique le carreau sur cette couche ; on enduit les côtés du carreau de mortier, afin qu’il se lie bien avec le carreau contigu ; on en pose ainsi une rangée entiere ; on s’assûre que cette rangée est bien droite &amp; bien de niveau, par une longue regle, &amp; par l’instrument appellé <i>niveau</i>. L’étendue d’une chambre &amp; la figure du carreau étant données, il n’est pas difficile de trouver le nombre de carreaux qui y entreront ; il ne s’agit que de chercher la surface de la chambre &amp; celle du carreau, &amp; diviser la premiere par la seconde. S’il s’agit de former un pavé dont l’aspect soit agréable à la vûe, avec des carreaux mi-partis de deux couleurs, <i>Voyez l’article</i> <a href=\"/wiki/L%E2%80%99Encyclop%C3%A9die/1re_%C3%A9dition/CARREAU\" title=\"L’Encyclopédie/1re édition/CARREAU\"><span class=\"sc\">Carreau</span></a> <i>en Architecture</i>. \n \n</p>\n</div>",
    "texthtml_re": "<div class=\"prp-pages-output\" lang=\"fr\">\n\n<p>CARRELER, v. act. c’est paver une chambre, une salle, <i>&amp;c.</i> avec des carreaux. Ce travail s’exécute au mortier &amp; à la brique. On commence par répandre sur la surface à <i>carreler</i> une couche plus ou moins épaisse d’excellent mortier ; on applique le carreau sur cette couche ; on enduit les côtés du carreau de mortier, afin qu’il se lie bien avec le carreau contigu ; on en pose ainsi une rangée entiere ; on s’assûre que cette rangée est bien droite &amp; bien de niveau, par une longue regle, &amp; par l’instrument appellé <i>niveau</i>. L’étendue d’une chambre &amp; la figure du carreau étant données, il n’est pas difficile de trouver le nombre de carreaux qui y entreront ; il ne s’agit que de chercher la surface de la chambre &amp; celle du carreau, &amp; diviser la premiere par la seconde. S’il s’agit de former un pavé dont l’aspect soit agréable à la vûe, avec des carreaux mi-partis de deux couleurs, <i><span type=\"bold\">Voyez</span> l’article</i> <a href=\"/wiki/L%E2%80%99Encyclop%C3%A9die/1re_%C3%A9dition/CARREAU\" title=\"L’Encyclopédie/1re édition/CARREAU\"><span class=\"sc\">Carreau</span></a> <i>en Architecture</i>. \n \n</p>\n</div>",
    "title": "CARRELER",
    "tome": "2",
    "url": "https://fr.wikisource.org/wiki/L%E2%80%99Encyclop%C3%A9die/1re_%C3%A9dition/CARRELER"
}