{
    "authors": [
        "Denis Diderot"
    ],
    "enc_link": "http://enccre.academie-sciences.fr/encyclopedie/article/v2-4180-0/",
    "item_id": "2-4190",
    "next": "2-4191",
    "pages": "807",
    "prev": "2-4189",
    "publish_year": "1751",
    "texthtml": "<div class=\"prp-pages-output\" lang=\"fr\">\n\n<p>* CELLITES, s. m. pl. (<i>Hist. ecclés</i>) nom que l’on\ndonne aux religieux d’un ordre dont il y a des maisons,\nsur-tout en Allemagne &amp; dans les Pays-Bas.\nLeur fondateur étoit un Romain nommé <i>Meccio</i>,\nc’est pourquoi les Italiens les appellent <i>Mecciens</i>. Ils\nsuivent la regle de S. Augustin, &amp; leur institut fut\napprouvé par le pape Pie II. qui leur accorda une\nbulle. Ils s’occupent à soigner les infirmes, sur-tout\nceux qui sont attaqués de maladies contagieuses,\ncomme la peste, <i>&amp;c.</i> à enterrer les morts, &amp; à servir \nles fous : ils ont beaucoup de rapport à nos Freres\nde la Charité.\n \n</p>\n</div>",
    "texthtml_re": "<div class=\"prp-pages-output\" lang=\"fr\">\n\n<p>* CELLITES, s. m. pl. (<i>Hist. ecclés</i>) nom que l’on\ndonne aux religieux d’un ordre dont il y a des maisons,\nsur-tout en Allemagne &amp; dans les Pays-Bas.\nLeur fondateur étoit un Romain nommé <i>Meccio</i>,\nc’est pourquoi les Italiens les appellent <i>Mecciens</i>. Ils\nsuivent la regle de S. Augustin, &amp; leur institut fut\napprouvé par le pape Pie II. qui leur accorda une\nbulle. Ils s’occupent à soigner les infirmes, sur-tout\nceux qui sont attaqués de maladies contagieuses,\ncomme la peste, <i>&amp;c.</i> à enterrer les morts, &amp; à servir \nles fous : ils ont beaucoup de rapport à nos Freres\nde la Charité.\n \n</p>\n</div>",
    "title": "CELLITES",
    "tome_r": "II",
    "url": "https://fr.wikisource.org/wiki/L%E2%80%99Encyclop%C3%A9die/1re_%C3%A9dition/CELLITES"
}