{
    "authors": [
        "Denis Diderot"
    ],
    "enc_link": "http://enccre.academie-sciences.fr/encyclopedie/article/v2-432-0/",
    "item_id": "2-423",
    "next": "2-424",
    "pages": "75",
    "prev": "2-422",
    "publish_year": "1751",
    "texthtml": "<div class=\"prp-pages-output\" lang=\"fr\">\n\n<p>* BARDARIOTES, s. m. pl. (<i>Hist. anc.</i>) soldats\nde la garde de l’empereur de Constantinople. Ils\nétoient vêtus de rouge, couverts d’un bonnet à la\nPersanne, appellé <i>augurot</i>, &amp; bordé de drap couleur\nde citron, &amp; armés de bâtons &amp; de baguettes, pour\néloigner le peuple du passage de l’empereur. Ils veilloient \naux portes du palais. Ils étoient Persans d’origine.\nIls avoient pris le nom de <i>bardariotes</i>, du fleuve \nBardarius, sur lequel un des empereurs, qu’on ne\nnomme pas, les avoit transportés. Nicétas leur\ndonne les noms de <i>bardouques</i> &amp; de <i>manclavites</i>. Leur\nposte à l’armée étoit au septentrion de la tente impériale,\noù ils faisoient la garde. Ils obéissoient au <i>primicerius</i>, \nou <i>comite de la cour</i>. Macri pense que les\n<i>bardariotes</i> sont les mêmes que les <i>barbutes</i>.\n \n</p>\n</div>",
    "texthtml_re": "<div class=\"prp-pages-output\" lang=\"fr\">\n\n<p>* BARDARIOTES, s. m. pl. (<i>Hist. anc.</i>) soldats\nde la garde de l’empereur de Constantinople. Ils\nétoient vêtus de rouge, couverts d’un bonnet à la\nPersanne, appellé <i>augurot</i>, &amp; bordé de drap couleur\nde citron, &amp; armés de bâtons &amp; de baguettes, pour\néloigner le peuple du passage de l’empereur. Ils veilloient \naux portes du palais. Ils étoient Persans d’origine.\nIls avoient pris le nom de <i>bardariotes</i>, du fleuve \nBardarius, sur lequel un des empereurs, qu’on ne\nnomme pas, les avoit transportés. Nicétas leur\ndonne les noms de <i>bardouques</i> &amp; de <i>manclavites</i>. Leur\nposte à l’armée étoit au septentrion de la tente impériale,\noù ils faisoient la garde. Ils obéissoient au <i>primicerius</i>, \nou <i>comite de la cour</i>. Macri pense que les\n<i>bardariotes</i> sont les mêmes que les <i>barbutes</i>.\n \n</p>\n</div>",
    "title": "BARDARIOTES",
    "tome_r": "II",
    "url": "https://fr.wikisource.org/wiki/L%E2%80%99Encyclop%C3%A9die/1re_%C3%A9dition/BARDARIOTES"
}