{
    "authors": [
        "Edme-François Mallet"
    ],
    "enc_link": "http://enccre.academie-sciences.fr/encyclopedie/article/v2-817-0/",
    "item_id": "2-821",
    "next": "2-822",
    "pages": "190",
    "prev": "2-820",
    "publish_year": "1751",
    "texthtml": "<div class=\"prp-pages-output\" lang=\"fr\">\n\n<p>BEELZEPHON, <i>ou</i> BAAL-TSEPHON, (<i>Myth.</i>) \nidole des Egyptiens. Ce mot est composé de <i>beel,  seigneur</i> ou <i>dieu</i>, &amp; de <i>tsephon, caché</i>, ou <i>le septentrion</i>, \ncomme qui diroit <i>le dieu caché</i>, ou <i>le dieu du  nord</i>. On donna aussi ce nom au lieu où cette idole \nétoit placée, sur les confins de l’Egypte vers la mer \nRouge. Rabi Aben-Ezra dit que c’étoit un talisman \nd’airain que les magiciens de Pharaon avoient fait \npour empêcher que les Israélites ne sortissent de l’Egypte. D’autres disent que les Egyptiens dressoient \nde ces talismans en tous les endroits par où les ennemis \npouvoient aisément faire irruption dans l’Egypte, \nafin que leurs efforts fussent arrêtés par la force \nmagique de ces idoles. Il y en a qui croyent que \ncette idole de <i>beelzephon</i> avoit la figure d’un chien, &amp; \nqu’elle aboyoit lorsque quelqu’Israélite passoit par \nce lieu pour s’enfuir. <i>Kircher, Œdipus Ægiptiacus,  tome I.</i> (<i>G</i>) \n \n</p>\n</div>",
    "texthtml_re": "<div class=\"prp-pages-output\" lang=\"fr\">\n\n<p>BEELZEPHON, <i>ou</i> BAAL-TSEPHON, (<i>Myth.</i>) \nidole des Egyptiens. Ce mot est composé de <i>beel,  seigneur</i> ou <i>dieu</i>, &amp; de <i>tsephon, caché</i>, ou <i>le septentrion</i>, \ncomme qui diroit <i>le dieu caché</i>, ou <i>le dieu du  nord</i>. On donna aussi ce nom au lieu où cette idole \nétoit placée, sur les confins de l’Egypte vers la mer \nRouge. Rabi Aben-Ezra dit que c’étoit un talisman \nd’airain que les magiciens de Pharaon avoient fait \npour empêcher que les Israélites ne sortissent de l’Egypte. D’autres disent que les Egyptiens dressoient \nde ces talismans en tous les endroits par où les ennemis \npouvoient aisément faire irruption dans l’Egypte, \nafin que leurs efforts fussent arrêtés par la force \nmagique de ces idoles. Il y en a qui croyent que \ncette idole de <i>beelzephon</i> avoit la figure d’un chien, &amp; \nqu’elle aboyoit lorsque quelqu’Israélite passoit par \nce lieu pour s’enfuir. <i>Kircher, Œdipus Ægiptiacus, <span type=\"proposed\"> tome </span>I.</i> (<i>G</i>) \n \n</p>\n</div>",
    "title": "BEELZEPHON, ou BAAL-TSEPHON",
    "tome_r": "II",
    "url": "https://fr.wikisource.org/wiki/L%E2%80%99Encyclop%C3%A9die/1re_%C3%A9dition/BEELZEPHON,_ou_BAAL-TSEPHON"
}