{
    "authors": [
        "Denis Diderot"
    ],
    "enc_link": "http://enccre.academie-sciences.fr/encyclopedie/article/v2-843-0/",
    "item_id": "2-847",
    "next": "2-848",
    "pages": "192",
    "prev": "2-846",
    "publish_year": "1751",
    "texthtml": "<div class=\"prp-pages-output\" lang=\"fr\">\n\n<p>* BEIGE, s. f. (<i>Commerce.</i>) serge noire, grise ou\ntannée, que l’on fabrique en Poitou avec la laine,\ntelle qu’on l’enleve de dessus le mouton, tant à la\nchaîne qu’à la trame. Elle doit avoir trente-huit à\ntrente-neuf portées, &amp; chaque portée vingt fils.\n \n</p>\n</div>",
    "texthtml_re": "<div class=\"prp-pages-output\" lang=\"fr\">\n\n<p>* BEIGE, s. f. (<i>Commerce.</i>) serge noire, grise ou\ntannée, que l’on fabrique en Poitou avec la laine,\ntelle qu’on l’enleve de dessus le mouton, tant à la\nchaîne qu’à la trame. Elle doit avoir trente-huit à\ntrente-neuf portées, &amp; chaque portée vingt fils.\n \n</p>\n</div>",
    "title": "BEIGE",
    "tome_r": "II",
    "url": "https://fr.wikisource.org/wiki/L%E2%80%99Encyclop%C3%A9die/1re_%C3%A9dition/BEIGE"
}