{
    "authors": [
        "Denis Diderot"
    ],
    "enc_link": "http://enccre.academie-sciences.fr/encyclopedie/article/v2-930-0/",
    "item_id": "2-934",
    "next": "2-935",
    "pages": "200",
    "prev": "2-933",
    "publish_year": "1751",
    "texthtml": "<div class=\"prp-pages-output\" lang=\"fr\">\n\n<p>* BEMILUCIUS, (<i>Mythol.</i>) surnom d’un Jupiter \njeune &amp; sans barbe, qui avoit ses autels dans la province \nque nous nommons <i>la Bourgogne</i>, aux environs \nde l’endroit où est maintenant l’abbaye de Flavigny. \n \n</p>\n</div>",
    "texthtml_re": "<div class=\"prp-pages-output\" lang=\"fr\">\n\n<p>* BEMILUCIUS, (<i>Mythol.</i>) surnom d’un Jupiter \njeune &amp; sans barbe, qui avoit ses autels dans la province \nque nous nommons <i>la Bourgogne</i>, aux environs \nde l’endroit où est maintenant l’abbaye de Flavigny. \n \n</p>\n</div>",
    "title": "BEMILUCIUS",
    "tome_r": "II",
    "url": "https://fr.wikisource.org/wiki/L%E2%80%99Encyclop%C3%A9die/1re_%C3%A9dition/BEMILUCIUS"
}